opendental/__init__.py
opendental/client.py
opendental/exceptions.py
opendental/api/__init__.py
opendental/base/__init__.py
opendental/base/models.py
opendental/base/resource.py
opendental/models/__init__.py
opendental/resources/__init__.py
opendental/resources/account_modules/__init__.py
opendental/resources/account_modules/client.py
opendental/resources/account_modules/models.py
opendental/resources/account_modules/types.py
opendental/resources/adjustments/__init__.py
opendental/resources/adjustments/client.py
opendental/resources/adjustments/models.py
opendental/resources/adjustments/types.py
opendental/resources/allergies/__init__.py
opendental/resources/allergies/client.py
opendental/resources/allergies/models.py
opendental/resources/allergies/types.py
opendental/resources/appointment_types/__init__.py
opendental/resources/appointment_types/client.py
opendental/resources/appointment_types/models.py
opendental/resources/appointment_types/types.py
opendental/resources/appointments/__init__.py
opendental/resources/appointments/client.py
opendental/resources/appointments/models.py
opendental/resources/appointments/types.py
opendental/resources/appt_field_defs/__init__.py
opendental/resources/appt_field_defs/client.py
opendental/resources/appt_field_defs/models.py
opendental/resources/appt_field_defs/types.py
opendental/resources/appt_fields/__init__.py
opendental/resources/appt_fields/client.py
opendental/resources/appt_fields/models.py
opendental/resources/appt_fields/types.py
opendental/resources/auto_notes/__init__.py
opendental/resources/auto_notes/client.py
opendental/resources/auto_notes/models.py
opendental/resources/auto_notes/types.py
opendental/resources/benefits/__init__.py
opendental/resources/benefits/client.py
opendental/resources/benefits/exceptions.py
opendental/resources/benefits/models.py
opendental/resources/benefits/types.py
opendental/resources/benefits/validators.py
opendental/resources/carriers/__init__.py
opendental_sdk-1.2.3.dist-info/METADATA
opendental_sdk-1.2.3.dist-info/WHEEL
opendental_sdk-1.2.3.dist-info/top_level.txt
opendental_sdk-1.2.3.dist-info/RECORD
