Metadata-Version: 2.4
Name: opendental-sdk
Version: 1.2.3
Summary: Simple, domain-driven Python SDK for Open Dental API with full type safety
Author-email: Open Dental SDK Team <support@opendental-sdk.com>
Project-URL: Homepage, https://github.com/opendental/python-sdk
Project-URL: Bug Reports, https://github.com/opendental/python-sdk/issues
Project-URL: Source, https://github.com/opendental/python-sdk
Classifier: Development Status :: 4 - Beta
Classifier: Intended Audience :: Developers
Classifier: License :: OSI Approved :: MIT License
Classifier: Operating System :: OS Independent
Classifier: Programming Language :: Python :: 3
Classifier: Programming Language :: Python :: 3.8
Classifier: Programming Language :: Python :: 3.9
Classifier: Programming Language :: Python :: 3.10
Classifier: Programming Language :: Python :: 3.11
Classifier: Programming Language :: Python :: 3.12
Requires-Python: >=3.8
Requires-Dist: requests>=2.25.1
Requires-Dist: urllib3>=1.26.0
Requires-Dist: pydantic>=2.0.0
Provides-Extra: dev
Requires-Dist: pytest>=7.0.0; extra == "dev"
Requires-Dist: pytest-cov>=4.0.0; extra == "dev"
Requires-Dist: responses>=0.23.0; extra == "dev"
Requires-Dist: black>=23.0.0; extra == "dev"
Requires-Dist: isort>=5.12.0; extra == "dev"
Requires-Dist: flake8>=6.0.0; extra == "dev"
Requires-Dist: mypy>=1.0.0; extra == "dev"
